<?xml version="1.0" encoding="UTF-8" standalone="no"?>
<?OFX OFXHEADER=200 VERSION=201 SECURITY=NONE OLDFILEUID=NONE NEWFILEUID=NONE?>
<OFX>
  <SIGNONMSGSRQV1>
    <SONRQ>
      <DTCLIENT>20180627150116</DTCLIENT>
      <USERID>SysUserHere</USERID>
      <USERPASS>SysPasswordHere</USERPASS>
      <LANGUAGE>ENG</LANGUAGE>
      <FI>
        <ORG>Fiserv</ORG>
        <FID>999999999</FID>
      </FI>
      <APPID>COASP</APPID>
      <APPVER>0100</APPVER>
      <USERS.TYPE>EMPLOYEE</USERS.TYPE>
    </SONRQ>
  </SIGNONMSGSRQV1>
  <BANKMSGSRQV1>
    <STPCHKTRNRQ>
      <TRNUID>cf1cccfb-6031-474c-967d-afb4c9bfdbd3</TRNUID>
      <STPCHKRQ>
        <BANKACCTFROM>
          <ACCTTYPE>CHECKING</ACCTTYPE>
          <USERS.ACCTTYPE>hostacct1</USERS.ACCTTYPE>
        </BANKACCTFROM>
        <CHKRANGE>
          <CHKNUMSTART>101</CHKNUMSTART>
          <CHKNUMEND>200</CHKNUMEND>
        </CHKRANGE>
        <USERS.REASON>TestingMutiple</USERS.REASON>
      </STPCHKRQ>
    </STPCHKTRNRQ>
  </BANKMSGSRQV1>
</OFX>